django_telegram_bot-0.6.0.dist-info/DESCRIPTION.rst
django_telegram_bot-0.6.0.dist-info/METADATA
django_telegram_bot-0.6.0.dist-info/RECORD
django_telegram_bot-0.6.0.dist-info/WHEEL
django_telegram_bot-0.6.0.dist-info/metadata.json
django_telegram_bot-0.6.0.dist-info/top_level.txt
telegrambot/__init__.py
telegrambot/admin.py
telegrambot/serializers.py
telegrambot/urls.py
telegrambot/views.py
telegrambot/bot_views/__init__.py
telegrambot/bot_views/decorators.py
telegrambot/bot_views/login.py
telegrambot/bot_views/generic/__init__.py
telegrambot/bot_views/generic/base.py
telegrambot/bot_views/generic/compound.py
telegrambot/bot_views/generic/detail.py
telegrambot/bot_views/generic/list.py
telegrambot/bot_views/generic/responses.py
telegrambot/handlers/__init__.py
telegrambot/handlers/conf.py
telegrambot/handlers/resolver.py
telegrambot/migrations/0001_initial.py
telegrambot/migrations/0002_bot.py
telegrambot/migrations/0003_auto_20160202_1803.py
telegrambot/migrations/__init__.py
telegrambot/models/__init__.py
telegrambot/models/auth.py
telegrambot/models/bot.py
telegrambot/models/telegram_api.py
telegrambot/templates/telegrambot/authentication.html
telegrambot/templates/telegrambot/messages/login_required.txt
telegrambot/templatetags/__init__.py
telegrambot/templatetags/telegrambot_filters.py
telegrambot/test/__init__.py
telegrambot/test/testcases.py
telegrambot/test/factories/__init__.py
telegrambot/test/factories/auth.py
telegrambot/test/factories/bot.py
telegrambot/test/factories/telegram_lib.py
telegrambot/test/factories/user.py
