Metadata-Version: 1.1
Name: django-telegram-bot
Version: 0.6.0
Summary: Django app to write Telegram bots
Home-page: https://github.com/jlmadurga/django-telegram-bot
Author: Juan Madurga
Author-email: jlmadurga@gmail.com
License: BSD
Keywords: django-telegram-bot
Platform: UNKNOWN
Classifier: Development Status :: 3 - Alpha
Classifier: Framework :: Django
Classifier: Framework :: Django :: 1.8
Classifier: Framework :: Django :: 1.9
Classifier: Intended Audience :: Developers
Classifier: License :: OSI Approved :: BSD License
Classifier: Natural Language :: English
Classifier: Programming Language :: Python :: 2
Classifier: Programming Language :: Python :: 2.7
Classifier: Programming Language :: Python :: 3
Classifier: Programming Language :: Python :: 3.4
Classifier: Programming Language :: Python :: 3.5
